torrentpy/__init__.py
torrentpy/batch.py
torrentpy/database.py
torrentpy/inout.py
torrentpy/knowledgebase.py
torrentpy/network.py
torrentpy/timeframe.py
torrentpy/models/__init__.py
torrentpy/models/model.py
torrentpy/models/catchment/__init__.py
torrentpy/models/catchment/inca.py
torrentpy/models/catchment/smart.py
torrentpy/models/lake/__init__.py
torrentpy/models/river/__init__.py
torrentpy/models/river/inca.py
torrentpy/models/river/smart.py
torrentpy/utils/__init__.py
torrentpy/utils/connectivity.py
torrentpy-0.2.0.dist-info/METADATA
torrentpy-0.2.0.dist-info/RECORD
torrentpy-0.2.0.dist-info/WHEEL
torrentpy-0.2.0.dist-info/top_level.txt
