Metadata-Version: 2.1
Name: torrentpy
Version: 0.2.0
Summary: TORRENTpy: a tool for TranspORt thRough the catchmEnt NeTwork
Home-page: https://github.com/ThibHlln/torrentpy
Author: Thibault Hallouin, Michael Bruen, and Eva Mockler
Author-email: thibault.hallouin@ucdconnect.ie
License: GPLv3
Platform: UNKNOWN
Classifier: Development Status :: 4 - Beta
Classifier: Natural Language :: English
Classifier: Intended Audience :: Science/Research
Classifier: Intended Audience :: Developers
Classifier: Topic :: Scientific/Engineering
Classifier: Operating System :: MacOS
Classifier: Operating System :: Microsoft :: Windows
Classifier: Operating System :: POSIX :: Linux
Classifier: License :: OSI Approved :: GNU General Public License v3 (GPLv3)
Classifier: Programming Language :: Python :: 2
Classifier: Programming Language :: Python :: 2.7
Classifier: Programming Language :: Python :: 3
Classifier: Programming Language :: Python :: 3.5
Classifier: Programming Language :: Python :: 3.6
Classifier: Programming Language :: Python :: Implementation :: CPython
Provides-Extra: with_graphviz
Provides-Extra: with_netcdf
Provides-Extra: with_smartcpp
Provides-Extra: with_all_extras
Requires-Dist: numpy
Requires-Dist: future
Provides-Extra: with_all_extras
Requires-Dist: netCDF4; extra == 'with_all_extras'
Requires-Dist: graphviz; extra == 'with_all_extras'
Requires-Dist: smartcpp; extra == 'with_all_extras'
Provides-Extra: with_graphviz
Requires-Dist: graphviz; extra == 'with_graphviz'
Provides-Extra: with_netcdf
Requires-Dist: netCDF4; extra == 'with_netcdf'
Provides-Extra: with_smartcpp
Requires-Dist: smartcpp; extra == 'with_smartcpp'
